libname/__init__.py
py_tempconv-0.1.0.dist-info/METADATA
py_tempconv-0.1.0.dist-info/WHEEL
py_tempconv-0.1.0.dist-info/RECORD
