Metadata-Version: 2.4
Name: py_tempconv
Version: 0.1.0
Summary: A comprehensive temperature conversion library.
Author-email: Manav Madan Rawal <manavrawalofficial@gmail.com>
License: MIT License
Classifier: License :: OSI Approved :: MIT License
Classifier: Operating System :: OS Independent
Classifier: Programming Language :: Python :: 3
Requires-Python: >=3.7
